[{"success": 3, "all": 5, "fail": 2, "skip": 0, "error": 0, "runtime": "214.30 S", "begin_time": "2025-08-20 15:36:28", "pass_rate": "60.00"}, {"success": 4, "all": 5, "fail": 1, "skip": 0, "error": 0, "runtime": "223.81 S", "begin_time": "2025-08-21 08:45:32", "pass_rate": "80.00"}, {"success": 2, "all": 5, "fail": 3, "skip": 0, "error": 0, "runtime": "153.99 S", "begin_time": "2025-08-21 09:00:12", "pass_rate": "40.00"}, {"success": 5, "all": 5, "fail": 0, "skip": 0, "error": 0, "runtime": "225.39 S", "begin_time": "2025-08-21 09:10:07", "pass_rate": "100.00"}]